pymemuc/__init__.py
pymemuc/_command.py
pymemuc/_constants.py
pymemuc/_control.py
pymemuc/_decorators.py
pymemuc/_manage.py
pymemuc/_memuc.py
pymemuc/exceptions.py
pymemuc/pymemuc.py
pymemuc/types.py
pymemuc-0.6.0.dist-info/LICENSE
pymemuc-0.6.0.dist-info/METADATA
pymemuc-0.6.0.dist-info/WHEEL
pymemuc-0.6.0.dist-info/RECORD
