Metadata-Version: 2.1
Name: pymemuc
Version: 0.6.0
Summary: A Python API for MEmu Android Emulator.
Home-page: https://github.com/pyclashbot/pymemuc
License: MIT
Keywords: memu,memuc,android-emulator,api
Author: Martin Miglio
Author-email: martin@pyclashbot.app
Requires-Python: >=3.9,<4.0
Classifier: License :: OSI Approved :: MIT License
Classifier: Programming Language :: Python
Classifier: Programming Language :: Python :: 3
Classifier: Programming Language :: Python :: 3.9
Classifier: Programming Language :: Python :: 3.10
Classifier: Programming Language :: Python :: 3.11
Classifier: Programming Language :: Python :: 3.12
Classifier: Topic :: Software Development :: Libraries :: Python Modules
Requires-Dist: typing-extensions (>=3.10.0) ; python_version < "3.10"
Project-URL: Documentation, https://pymemuc.pyclashbot.app/
Project-URL: Repository, https://github.com/pyclashbot/pymemuc
